{
   "filters":{
      "0":{
         "value":"christmas",
         "frontend_value":"Božićne"
      },
      "1":{
         "value":"summer",
         "frontend_value":"Ljetne"
      },
      "2":{
         "value":"universal",
         "frontend_value":"Univerzalne"
      },
      "3":{
         "value":"cars",
         "frontend_value":"Auti"
      },
      "4":{
         "value":"cats",
         "frontend_value":"Životinje"
      },
      "5":{
         "value":"animals",
         "frontend_value":"Mačke"
      },
      "6":{
         "value":"dogs",
         "frontend_value":"Psi"
      },
      "7":{
         "value":"dinosaurs",
         "frontend_value":"Dinosauri"
      }
   },
   "jars":[
      {
         "jar_id":"0",
         "avaliable":true,
         "img_number":4,
         "type":[
            "christmas"
         ],
         "size":"small, medium, large"
      },
      {
         "jar_id":"1",
         "avaliable":false,
         "img_number":4,
         "type":[
            "christmas"
         ]
      },
      {
         "jar_id":"2",
         "avaliable":true,
         "img_number":4,
         "type":[
            "christmas",
            "cars"
         ]
      },
      {
         "jar_id":"3",
         "avaliable":true,
         "img_number":4,
         "type":[
            "christmas",
            "cars"
         ]
      },
      {
         "jar_id":"4",
         "avaliable":true,
         "img_number":4,
         "type":[
            "christmas",
            "cars"
         ]
      },
      {
         "jar_id":"5",
         "avaliable":true,
         "img_number":4,
         "type":[
            "christmas"
         ]
      },
      {
         "jar_id":"6",
         "avaliable":false,
         "img_number":4,
         "type":[
            "christmas",
            "cars"
         ]
      },
      {
         "jar_id":"7",
         "avaliable":false,
         "img_number":4,
         "type":[
            "christmas"
         ]
      },
      {
         "jar_id":"8",
         "avaliable":false,
         "img_number":4,
         "type":[
            "christmas"
         ]
      },
      {
         "jar_id":"9",
         "avaliable":true,
         "img_number":4,
         "type":[
            "christmas"
         ]
      },
      {
         "jar_id":"10",
         "avaliable":false,
         "img_number":4,
         "type":[
            "christmas"
         ]
      },
      {
         "jar_id":"11",
         "avaliable":true,
         "img_number":4,
         "type":[
            "christmas",
            "cars"
         ]
      },
      {
         "jar_id":"12",
         "avaliable":false,
         "img_number":4,
         "type":[
            "christmas",
            "cars"
         ]
      },
      {
         "jar_id":"13",
         "avaliable":false,
         "img_number":4,
         "type":[
            "christmas",
            "cars"
         ]
      },
      {
         "jar_id":"14",
         "avaliable":true,
         "img_number":4,
         "type":[
            "christmas"
         ]
      },
      {
         "jar_id":"15",
         "avaliable":true,
         "img_number":4,
         "type":[
            "christmas"
         ]
      },
      {
         "jar_id":"16",
         "avaliable":true,
         "img_number":4,
         "type":[
            "christmas",
            "cars"
         ]
      },
      {
         "jar_id":"17",
         "avaliable":true,
         "img_number":4,
         "type":[
            "christmas",
            "cars"
         ]
      },
      {
         "jar_id":"18",
         "avaliable":true,
         "img_number":4,
         "type":[
            "christmas",
            "cars"
         ]
      },
      {
         "jar_id":"19",
         "avaliable":true,
         "img_number":4,
         "type":[
            "christmas",
            "cats",
            "animals"
         ]
      },
      {
         "jar_id":"20",
         "avaliable":false,
         "img_number":4,
         "type":[
            "christmas",
            "dogs",
            "animals"
         ]
      },
      {
         "jar_id":"21",
         "avaliable":true,
         "img_number":4,
         "type":[
            "christmas"
         ]
      },
      {
         "jar_id":"22",
         "avaliable":true,
         "img_number":4,
         "type":[
            "christmas"
         ]
      },
      {
         "jar_id":"23",
         "avaliable":false,
         "img_number":4,
         "type":[
            "christmas"
         ]
      },
      {
         "jar_id":"24",
         "avaliable":false,
         "img_number":4,
         "type":[
            "christmas"
         ]
      },
      {
         "jar_id":"25",
         "avaliable":false,
         "img_number":4,
         "type":[
            "christmas"
         ]
      },
      {
         "jar_id":"26",
         "avaliable":false,
         "img_number":4,
         "type":[
            "christmas"
         ]
      },
      {
         "jar_id":"27",
         "avaliable":true,
         "img_number":4,
         "type":[
            "christmas",
            "cars"
         ]
      },
      {
         "jar_id":"28",
         "avaliable":false,
         "img_number":4,
         "type":[
            "christmas"
         ]
      },
      {
         "jar_id":"29",
         "avaliable":true,
         "img_number":4,
         "type":[
            "christmas",
            "cars"
         ]
      },
      {
         "jar_id":"30",
         "avaliable":false,
         "img_number":4,
         "type":[
            "christmas",
            "cars"
         ]
      },
      {
         "jar_id":"31",
         "avaliable":false,
         "img_number":4,
         "type":[
            "christmas"
         ]
      },
      {
         "jar_id":"32",
         "avaliable":false,
         "img_number":4,
         "type":[
            "christmas"
         ]
      },
      {
         "jar_id":"33",
         "avaliable":false,
         "img_number":4,
         "type":[
            "christmas"
         ]
      },
      {
         "jar_id":"34",
         "avaliable":false,
         "img_number":4,
         "type":[
            "christmas"
         ]
      },
      {
         "jar_id":"35",
         "avaliable":false,
         "img_number":4,
         "type":[
            "christmas"
         ]
      },
      {
         "jar_id":"36",
         "avaliable":true,
         "img_number":4,
         "type":[
            "christmas"
         ]
      },
      {
         "jar_id":"37",
         "avaliable":false,
         "img_number":4,
         "type":[
            "christmas"
         ]
      },
      {
         "jar_id":"38",
         "avaliable":true,
         "img_number":4,
         "type":[
            "christmas",
            "cars"
         ]
      },
      {
         "jar_id":"39",
         "avaliable":true,
         "img_number":4,
         "type":[
            "christmas",
            "cars"
         ]
      },
      {
         "jar_id":"40",
         "avaliable":false,
         "img_number":4,
         "type":[
            "christmas",
            "cars"
         ]
      },
      {
         "jar_id":"41",
         "avaliable":true,
         "img_number":4,
         "type":[
            "christmas"
         ]
      },
      {
         "jar_id":"42",
         "avaliable":false,
         "img_number":4,
         "type":[
            "christmas"
         ]
      },
      {
         "jar_id":"43",
         "avaliable":true,
         "img_number":4,
         "type":[
            "christmas"
         ]
      },
      {
         "jar_id":"44",
         "avaliable":false,
         "img_number":4,
         "type":[
            "christmas"
         ]
      },
      {
         "jar_id":"45",
         "avaliable":false,
         "img_number":4,
         "type":[
            "christmas"
         ]
      },
      {
         "jar_id":"46",
         "avaliable":false,
         "img_number":4,
         "type":[
            "christmas",
            "cars"
         ]
      },
      {
         "jar_id":"47",
         "avaliable":false,
         "img_number":4,
         "type":[
            "christmas",
            "cats",
            "animals"
         ]
      },
      {
         "jar_id":"48",
         "avaliable":true,
         "img_number":4,
         "type":[
            "christmas"
         ]
      }
   ]
}